uts-lib/typed/io.uts
uts-lib/typed/typed-value.uts
uts-lib/utils/math.uts
uts-lib/utils/obj.uts
uts-lib/utils/uts-array.uts
uts-lib/utils/win32/async.uts
uts-lib/utils/win32/heapfuncs-nouse.uts
uts-lib/utils/win32/libheapfunc.o
uts-lib/uts/info.uts
utsc/__init__.py
utsc/ast_cleaner.py
utsc/ast_preprocessor.py
utsc/code_lowerer.py
utsc/compiler.py
utsc/optimizer.py
utsc/sequential_lexer.py
utsc/utils.py
utsc/uts_parser.py
untypedscript_utsc-1.0.3.dist-info/LICENSE
untypedscript_utsc-1.0.3.dist-info/METADATA
untypedscript_utsc-1.0.3.dist-info/WHEEL
untypedscript_utsc-1.0.3.dist-info/entry_points.txt
untypedscript_utsc-1.0.3.dist-info/top_level.txt
untypedscript_utsc-1.0.3.dist-info/RECORD
