Metadata-Version: 2.1
Name: untypedscript-utsc
Version: 1.0.3
Summary: UntypedScript original implementation compiler
Author-email: Carl Furtado <carlzfurtado@gmail.com>
License: MIT License
Project-URL: Homepage, https://github.com/User0332/UntypedScript
Project-URL: Documentation, https://untypedscript.readthedocs.io/en/latest/
Requires-Python: >=3.9
License-File: LICENSE
